nb_mypy/__init__.py
nb_mypy/_version.py
nb_mypy-1.0.6.dist-info/licenses/LICENSE
nb_mypy-1.0.6.dist-info/METADATA
nb_mypy-1.0.6.dist-info/WHEEL
nb_mypy-1.0.6.dist-info/top_level.txt
nb_mypy-1.0.6.dist-info/RECORD
