Metadata-Version: 2.4
Name: nb_mypy
Version: 1.0.6
Summary: Nb Mypy is a facility to automatically run mypy on Jupyter notebook cells as they are executed, whilst retaining information about the execution history.
Author: Tom Verhoeff
Author-email: Lars van den Haak <l.b.vandenhaak@gmail.com>
License-Expression: MIT
Project-URL: Homepage, https://gitlab.tue.nl/jupyter-projects/nb_mypy
Project-URL: Documentation, https://gitlab.tue.nl/jupyter-projects/nb_mypy/-/blob/master/Nb_Mypy.ipynb
Project-URL: Repository, https://gitlab.tue.nl/jupyter-projects/nb_mypy
Project-URL: Issues, https://github.com/sakehl/nb_mypy/issues
Keywords: Type Checking,Notebooks,IPython,MyPy
Classifier: Programming Language :: Python :: 3
Classifier: Operating System :: OS Independent
Classifier: Framework :: IPython
Requires-Python: >=3.11
License-File: LICENSE
Requires-Dist: astor<1,>=0.8
Requires-Dist: mypy<2,>=1
Requires-Dist: ipython<10,>=9.0
Dynamic: license-file
